sphinx_image_min/__init__.py
sphinx_image_min/sphinx_image_min.py
sphinx_image_min-1.0.9.dist-info/LICENSE
sphinx_image_min-1.0.9.dist-info/METADATA
sphinx_image_min-1.0.9.dist-info/WHEEL
sphinx_image_min-1.0.9.dist-info/RECORD
